Raspberry_Pi_Master_for_ESP32_I2C_SLAVE/__init__.py
Raspberry_Pi_Master_for_ESP32_I2C_SLAVE/crc8.py
Raspberry_Pi_Master_for_ESP32_I2C_SLAVE/packer.py
Raspberry_Pi_Master_for_ESP32_I2C_SLAVE/unpacker.py
tests/__init__.py
tests/test_Crc8.py
tests/test_Packer.py
tests/test_Unpacker.py
raspberrypi_esp32_i2c-0.0.6.dist-info/METADATA
raspberrypi_esp32_i2c-0.0.6.dist-info/WHEEL
raspberrypi_esp32_i2c-0.0.6.dist-info/top_level.txt
raspberrypi_esp32_i2c-0.0.6.dist-info/RECORD
