Metadata-Version: 2.1
Name: raspberrypi-esp32-i2c
Version: 0.0.6
Summary: use Raspberry Pi as master on ESP32 i2c     slave when use ESP32 i2c Slave c++ library
Home-page: https://github.com/MkLHX/Raspberry_Pi_Master_for_ESP32_I2C_SLAVE
Author: Mickael Lehoux
Author-email: mickael@lehoux.net
License: MIT
Project-URL: Source, https://github.com/MkLHX/            Raspberry_Pi_Master_for_ESP32_I2C_SLAVE
Project-URL: Bug Reports, https://github.com/MkLHX/            Raspberry_Pi_Master_for_ESP32_I2C_SLAVE/issues
Keywords: i2c driver python hardware diy iot raspberry pi
Platform: UNKNOWN
Classifier: Programming Language :: Python :: 3
Classifier: License :: OSI Approved :: MIT License
Classifier: Operating System :: OS Independent
Requires-Python: >=3.6.0
